mul_div/__init__.py
shubham_MUL_DIV-0.0.1.dist-info/LICENCE.txt
shubham_MUL_DIV-0.0.1.dist-info/METADATA
shubham_MUL_DIV-0.0.1.dist-info/WHEEL
shubham_MUL_DIV-0.0.1.dist-info/top_level.txt
shubham_MUL_DIV-0.0.1.dist-info/RECORD
